ununseptium/__init__.py
ununseptium/py.typed
ununseptium/ai/__init__.py
ununseptium/ai/explain.py
ununseptium/ai/features.py
ununseptium/ai/governance.py
ununseptium/ai/models.py
ununseptium/ai/sciml/__init__.py
ununseptium/ai/sciml/constraints.py
ununseptium/ai/sciml/neural_ode.py
ununseptium/ai/sciml/neural_operator.py
ununseptium/ai/sciml/pinn.py
ununseptium/aml/__init__.py
ununseptium/aml/cases.py
ununseptium/aml/reporting.py
ununseptium/aml/transactions.py
ununseptium/aml/typologies.py
ununseptium/aml/monitoring/__init__.py
ununseptium/aml/monitoring/graph.py
ununseptium/aml/monitoring/rules.py
ununseptium/aml/monitoring/statistical.py
ununseptium/aml/monitoring/streaming.py
ununseptium/cli/__init__.py
ununseptium/cli/main.py
ununseptium/core/__init__.py
ununseptium/core/canonical.py
ununseptium/core/config.py
ununseptium/core/errors.py
ununseptium/core/logging.py
ununseptium/core/schemas.py
ununseptium/kyc/__init__.py
ununseptium/kyc/documents.py
ununseptium/kyc/entity_resolution.py
ununseptium/kyc/identity.py
ununseptium/kyc/screening.py
ununseptium/kyc/workflows.py
ununseptium/mathstats/__init__.py
ununseptium/mathstats/dependence.py
ununseptium/mathstats/graphstats.py
ununseptium/mathstats/numerics.py
ununseptium/mathstats/point_process.py
ununseptium/mathstats/sequential.py
ununseptium/mathstats/tails.py
ununseptium/mathstats/uncertainty.py
ununseptium/model_zoo/__init__.py
ununseptium/model_zoo/catalog.py
ununseptium/model_zoo/loader.py
ununseptium/plugins/__init__.py
ununseptium/plugins/base.py
ununseptium/plugins/loader.py
ununseptium/security/__init__.py
ununseptium/security/access.py
ununseptium/security/audit.py
ununseptium/security/crypto.py
ununseptium/security/integrity.py
ununseptium/security/pii.py
ununseptium-1.0.0.dist-info/licenses/LICENSE
ununseptium-1.0.0.dist-info/METADATA
ununseptium-1.0.0.dist-info/WHEEL
ununseptium-1.0.0.dist-info/entry_points.txt
ununseptium-1.0.0.dist-info/top_level.txt
ununseptium-1.0.0.dist-info/RECORD
