Metadata-Version: 2.4
Name: ununseptium
Version: 1.0.0
Summary: State-of-the-art RegTech and Cybersecurity Python library for KYC/AML automation, data security, and AI-driven risk analysis
Author-email: Olaf Laitinen <olaf.laitinen@protonmail.com>
Maintainer-email: Olaf Laitinen <olaf.laitinen@protonmail.com>
License: Apache-2.0
Project-URL: Homepage, https://github.com/olaflaitinen/ununseptium
Project-URL: Documentation, https://github.com/olaflaitinen/ununseptium#readme
Project-URL: Repository, https://github.com/olaflaitinen/ununseptium.git
Project-URL: Issues, https://github.com/olaflaitinen/ununseptium/issues
Project-URL: Changelog, https://github.com/olaflaitinen/ununseptium/blob/main/CHANGELOG.md
Keywords: kyc,aml,regtech,compliance,cybersecurity,risk-management,machine-learning,fraud-detection,pii,audit,pinn,neural-ode,conformal-prediction
Classifier: Development Status :: 5 - Production/Stable
Classifier: Intended Audience :: Developers
Classifier: Intended Audience :: Financial and Insurance Industry
Classifier: Intended Audience :: Science/Research
Classifier: License :: OSI Approved :: Apache Software License
Classifier: Operating System :: OS Independent
Classifier: Programming Language :: Python :: 3
Classifier: Programming Language :: Python :: 3.11
Classifier: Programming Language :: Python :: 3.12
Classifier: Programming Language :: Python :: 3.13
Classifier: Topic :: Scientific/Engineering :: Artificial Intelligence
Classifier: Topic :: Security
Classifier: Topic :: Office/Business :: Financial
Classifier: Typing :: Typed
Requires-Python: >=3.11
License-File: LICENSE
Requires-Dist: pydantic<3.0,>=2.0
Requires-Dist: pydantic-settings<3.0,>=2.0
Requires-Dist: numpy<3.0,>=1.24
Requires-Dist: scipy<2.0,>=1.11
Requires-Dist: click<9.0,>=8.0
Requires-Dist: rich<14.0,>=13.0
Requires-Dist: structlog<25.0,>=23.0
Requires-Dist: httpx<1.0,>=0.25
Requires-Dist: tenacity<10.0,>=8.0
Requires-Dist: filelock<4.0,>=3.12
Provides-Extra: crypto
Requires-Dist: cryptography<44.0,>=41.0; extra == "crypto"
Provides-Extra: ai-torch
Requires-Dist: torch<3.0,>=2.0; extra == "ai-torch"
Provides-Extra: ai-prob
Requires-Dist: pymc<6.0,>=5.0; extra == "ai-prob"
Provides-Extra: ai-jax
Requires-Dist: jax<1.0,>=0.4; extra == "ai-jax"
Requires-Dist: jaxlib<1.0,>=0.4; extra == "ai-jax"
Provides-Extra: perf
Requires-Dist: numba<1.0,>=0.58; extra == "perf"
Provides-Extra: graph
Requires-Dist: networkx<4.0,>=3.0; extra == "graph"
Provides-Extra: graph-torch
Requires-Dist: torch-geometric<3.0,>=2.4; extra == "graph-torch"
Provides-Extra: docs
Requires-Dist: mkdocs<2.0,>=1.5; extra == "docs"
Requires-Dist: mkdocs-material<10.0,>=9.0; extra == "docs"
Requires-Dist: mkdocstrings[python]<1.0,>=0.24; extra == "docs"
Provides-Extra: dev
Requires-Dist: pytest<9.0,>=7.4; extra == "dev"
Requires-Dist: pytest-cov<6.0,>=4.0; extra == "dev"
Requires-Dist: pytest-asyncio<1.0,>=0.21; extra == "dev"
Requires-Dist: pytest-benchmark<5.0,>=4.0; extra == "dev"
Requires-Dist: hypothesis<7.0,>=6.80; extra == "dev"
Requires-Dist: ruff<1.0,>=0.1; extra == "dev"
Requires-Dist: pyright<2.0,>=1.1.340; extra == "dev"
Requires-Dist: pip-audit<3.0,>=2.6; extra == "dev"
Requires-Dist: bandit<2.0,>=1.7; extra == "dev"
Requires-Dist: pre-commit<4.0,>=3.5; extra == "dev"
Requires-Dist: build<2.0,>=1.0; extra == "dev"
Requires-Dist: twine<6.0,>=4.0; extra == "dev"
Provides-Extra: all
Requires-Dist: ununseptium[ai-torch,crypto,dev,docs,graph,perf]; extra == "all"
Dynamic: license-file
